busylight_core/__init__.py
busylight_core/exceptions.py
busylight_core/hardware.py
busylight_core/hid.py
busylight_core/light.py
busylight_core/mixins/__init__.py
busylight_core/mixins/colorable.py
busylight_core/mixins/taskable.py
busylight_core/vendors/__init__.py
busylight_core/vendors/agile_innovative/__init__.py
busylight_core/vendors/agile_innovative/agile_innovative_base.py
busylight_core/vendors/agile_innovative/blinkstick.py
busylight_core/vendors/agile_innovative/blinkstick_base.py
busylight_core/vendors/agile_innovative/blinkstick_flex.py
busylight_core/vendors/agile_innovative/blinkstick_nano.py
busylight_core/vendors/agile_innovative/blinkstick_pro.py
busylight_core/vendors/agile_innovative/blinkstick_square.py
busylight_core/vendors/agile_innovative/blinkstick_strip.py
busylight_core/vendors/agile_innovative/implementation/__init__.py
busylight_core/vendors/agile_innovative/implementation/state.py
busylight_core/vendors/compulab/__init__.py
busylight_core/vendors/compulab/compulab_base.py
busylight_core/vendors/compulab/fit_statusb.py
busylight_core/vendors/embrava/__init__.py
busylight_core/vendors/embrava/blynclight.py
busylight_core/vendors/embrava/blynclight_mini.py
busylight_core/vendors/embrava/blynclight_plus.py
busylight_core/vendors/embrava/embrava_base.py
busylight_core/vendors/embrava/implementation/__init__.py
busylight_core/vendors/embrava/implementation/enums.py
busylight_core/vendors/embrava/implementation/fields.py
busylight_core/vendors/embrava/implementation/state.py
busylight_core/vendors/epos/__init__.py
busylight_core/vendors/epos/busylight.py
busylight_core/vendors/epos/epos_base.py
busylight_core/vendors/epos/implementation/__init__.py
busylight_core/vendors/epos/implementation/enums.py
busylight_core/vendors/epos/implementation/fields.py
busylight_core/vendors/epos/implementation/state.py
busylight_core/vendors/kuando/__init__.py
busylight_core/vendors/kuando/busylight_alpha.py
busylight_core/vendors/kuando/busylight_base.py
busylight_core-0.15.2.dist-info/WHEEL
busylight_core-0.15.2.dist-info/METADATA
busylight_core-0.15.2.dist-info/RECORD
