Metadata-Version: 2.4
Name: busylight-core
Version: 0.15.2
Summary: Busylight Core Implementation for Humans, presumably like you!
Author: JnyJny
Author-email: JnyJny <erik.oshaughnessy@gmail.com>
License-Expression: Apache-2.0
Classifier: Development Status :: 4 - Beta
Classifier: Operating System :: OS Independent
Classifier: Intended Audience :: Developers
Classifier: Intended Audience :: End Users/Desktop
Classifier: Environment :: Console
Classifier: Topic :: Utilities
Classifier: Programming Language :: Python
Classifier: Programming Language :: Python :: 3
Classifier: Programming Language :: Python :: 3.8
Requires-Dist: loguru
Requires-Dist: pyserial>=3.5
Requires-Dist: hidapi>=0.14.0.post4
Requires-Python: >=3.11, <4.0
Project-URL: Documentation, https://JnyJny.github.io/busylight_core/
Project-URL: Issues, https://github.com/JnyJny/busylight_core/issues
Project-URL: Source, https://github.com/JnyJny/busylight_core
